fastcpu/__init__.py
fastcpu/cli.py
fastcpu/core.py
fastcpu-1.5.0.dist-info/LICENSE
fastcpu-1.5.0.dist-info/METADATA
fastcpu-1.5.0.dist-info/WHEEL
fastcpu-1.5.0.dist-info/entry_points.txt
fastcpu-1.5.0.dist-info/top_level.txt
fastcpu-1.5.0.dist-info/RECORD
