Metadata-Version: 2.1
Name: fastcpu
Version: 1.5.0
Summary: A queue service for quickly running scripts sequentially to use all your CPUs efficiently
Home-page: https://github.com/tawanda/fastcpu
Author: Tawanda Minya
Author-email: tminya@gmail.com
License: UNKNOWN
Project-URL: Bug Tracker, https://github.com/tawanda/fastcpu/issues
Platform: UNKNOWN
Classifier: Programming Language :: Python :: 3
Classifier: License :: OSI Approved :: The Unlicense (Unlicense)
Classifier: Operating System :: OS Independent
Requires-Python: >=3.0
Requires-Dist: fastcore
Requires-Dist: psutil
